{"assets/fonts/Comfortaa-Bold.ttf":["assets/fonts/Comfortaa-Bold.ttf"],"assets/fonts/Comfortaa-Light.ttf":["assets/fonts/Comfortaa-Light.ttf"],"assets/fonts/Comfortaa-Medium.ttf":["assets/fonts/Comfortaa-Medium.ttf"],"assets/fonts/Comfortaa-Regular.ttf":["assets/fonts/Comfortaa-Regular.ttf"],"assets/fonts/Comfortaa-SemiBold.ttf":["assets/fonts/Comfortaa-SemiBold.ttf"],"assets/icons/camera.svg":["assets/icons/camera.svg"],"assets/icons/dd-logo.png":["assets/icons/dd-logo.png"],"assets/icons/dstu-logo.png":["assets/icons/dstu-logo.png"],"assets/icons/error.png":["assets/icons/error.png"],"assets/icons/stars.svg":["assets/icons/stars.svg"],"assets/icons/successfully.png":["assets/icons/successfully.png"],"assets/icons/vk-logo.svg":["assets/icons/vk-logo.svg"]}